provide/__init__.py
provide/foundation/__init__.py
provide/foundation/py.typed
provide/foundation/archive/__init__.py
provide/foundation/archive/base.py
provide/foundation/archive/bzip2.py
provide/foundation/archive/defaults.py
provide/foundation/archive/gzip.py
provide/foundation/archive/limits.py
provide/foundation/archive/operations.py
provide/foundation/archive/security.py
provide/foundation/archive/tar.py
provide/foundation/archive/types.py
provide/foundation/archive/xz.py
provide/foundation/archive/zip.py
provide/foundation/archive/zstd.py
provide/foundation/cli/__init__.py
provide/foundation/cli/base.py
provide/foundation/cli/decorators.py
provide/foundation/cli/deps.py
provide/foundation/cli/errors.py
provide/foundation/cli/helpers.py
provide/foundation/cli/main.py
provide/foundation/cli/shutdown.py
provide/foundation/cli/utils.py
provide/foundation/cli/click/__init__.py
provide/foundation/cli/click/adapter.py
provide/foundation/cli/click/builder.py
provide/foundation/cli/click/commands.py
provide/foundation/cli/click/hierarchy.py
provide/foundation/cli/click/parameters.py
provide/foundation/cli/commands/__init__.py
provide/foundation/cli/commands/config.py
provide/foundation/cli/commands/deps.py
provide/foundation/cli/commands/process.py
provide/foundation/cli/commands/logs/__init__.py
provide/foundation/cli/commands/logs/constants.py
provide/foundation/cli/commands/logs/generate.py
provide/foundation/cli/commands/logs/generator.py
provide/foundation/cli/commands/logs/query.py
provide/foundation/cli/commands/logs/send.py
provide/foundation/cli/commands/logs/stats.py
provide/foundation/cli/commands/logs/tail.py
provide/foundation/concurrency/__init__.py
provide/foundation/concurrency/async_locks.py
provide/foundation/concurrency/core.py
provide/foundation/concurrency/locks.py
provide/foundation/config/__init__.py
provide/foundation/config/base.py
provide/foundation/config/bootstrap.py
provide/foundation/config/converters.py
provide_foundation-0.3.0.post1.dist-info/licenses/LICENSE
provide_foundation-0.3.0.post1.dist-info/METADATA
provide_foundation-0.3.0.post1.dist-info/WHEEL
provide_foundation-0.3.0.post1.dist-info/entry_points.txt
provide_foundation-0.3.0.post1.dist-info/top_level.txt
provide_foundation-0.3.0.post1.dist-info/RECORD
