Metadata-Version: 2.4
Name: provide-foundation
Version: 0.3.0.post1
Summary: A comprehensive Python foundation library for building robust applications with structured logging, CLI framework, configuration management, and essential building blocks.
Author-email: Tim Perkins <code@tim.life>
Maintainer-email: "provide.io" <code@provide.io>
License-Expression: Apache-2.0
Project-URL: Homepage, https://github.com/provide-io/provide-foundation
Project-URL: Documentation, https://foundry.provide.io/foundation/
Project-URL: Repository, https://github.com/provide-io/provide-foundation
Project-URL: Issues, https://github.com/provide-io/provide-foundation/issues
Project-URL: Examples, https://github.com/provide-io/provide-foundation/tree/main/examples
Keywords: telemetry,logging,tracing,python,pyvider
Classifier: Development Status :: 4 - Beta
Classifier: Intended Audience :: Developers
Classifier: Operating System :: OS Independent
Classifier: Programming Language :: Python :: 3.11
Classifier: Programming Language :: Python :: 3.12
Classifier: Programming Language :: Python :: 3.13
Classifier: Programming Language :: Python :: 3.14
Classifier: Topic :: System :: Logging
Classifier: Topic :: System :: Monitoring
Classifier: Topic :: Software Development :: Libraries :: Python Modules
Classifier: Typing :: Typed
Requires-Python: >=3.11
License-File: LICENSE
Requires-Dist: attrs>=25.4.0
Requires-Dist: structlog>=25.5.0
Requires-Dist: tomli_w>=1.2.0
Provides-Extra: cli
Requires-Dist: click>=8.3.1; extra == "cli"
Provides-Extra: compression
Requires-Dist: zstandard>=0.25.0; extra == "compression"
Provides-Extra: crypto
Requires-Dist: cryptography>=45.0.7; extra == "crypto"
Provides-Extra: transport
Requires-Dist: httpx>=0.28.1; extra == "transport"
Provides-Extra: opentelemetry
Requires-Dist: opentelemetry-api>=1.22.0; extra == "opentelemetry"
Requires-Dist: opentelemetry-sdk>=1.22.0; extra == "opentelemetry"
Requires-Dist: opentelemetry-exporter-otlp-proto-grpc>=1.22.0; extra == "opentelemetry"
Requires-Dist: opentelemetry-exporter-otlp-proto-http>=1.22.0; extra == "opentelemetry"
Provides-Extra: platform
Requires-Dist: psutil>=7.0.0; extra == "platform"
Requires-Dist: py-cpuinfo>=9.0.0; extra == "platform"
Provides-Extra: process
Requires-Dist: psutil>=7.0.0; extra == "process"
Requires-Dist: setproctitle>=1.3.7; extra == "process"
Provides-Extra: extended
Requires-Dist: provide-foundation[platform,process]; extra == "extended"
Provides-Extra: all
Requires-Dist: provide-foundation[cli,compression,crypto,extended,opentelemetry,transport]; extra == "all"
Dynamic: license-file
